fastcd/__init__.py
fastcd/__main__.py
fastcd/config.json
fastcd/fastcd_hook.sh
fastcd/jumper.py
fastcd/key_picker.py
fastcd/search.py
fastcd/util.py
fastcd-1.3.0.data/scripts/fastcd
fastcd-1.3.0.dist-info/LICENSE
fastcd-1.3.0.dist-info/METADATA
fastcd-1.3.0.dist-info/WHEEL
fastcd-1.3.0.dist-info/top_level.txt
fastcd-1.3.0.dist-info/RECORD
