Metadata-Version: 2.1
Name: fastcd
Version: 1.3.0
Summary: Navigation command line tool for Linux/MacOs
Home-page: https://github.com/frazenshtein/fastcd
Author: frazenshtein
Author-email: ivansduck@gmail.com
License: GPLv2
Platform: UNKNOWN
Classifier: Development Status :: 5 - Production/Stable
Classifier: Environment :: Console
Classifier: Intended Audience :: Developers
Classifier: License :: OSI Approved :: GNU General Public License v2 (GPLv2)
Classifier: Operating System :: MacOS
Classifier: Operating System :: POSIX :: Linux
Classifier: Programming Language :: Python
Classifier: Programming Language :: Python :: 3
Classifier: Programming Language :: Python :: 3.4
Classifier: Programming Language :: Python :: 3.5
Classifier: Programming Language :: Python :: 3.6
Classifier: Programming Language :: Python :: 3.7
Classifier: Programming Language :: Python :: 3.8
Classifier: Topic :: Software Development
Classifier: Topic :: Utilities
Requires-Python: >=3.4
License-File: LICENSE
Requires-Dist: urwid (>=1.2)
